matrix_multiplier.v
module matrix_multiplier (
    clk, rst, start, matrix_a, matrix_b, done, result_c
);

    // Parameters
    parameter DATA_WIDTH = 8;
    parameter M = 8; // Rows of matrix A and C
    parameter N = 8; // Cols of matrix A and Rows of matrix B
    parameter P = 8; // Cols of matrix B and C

    input clk;
    input rst;
    input start;
    input [M*N*DATA_WIDTH-1:0] matrix_a;
    input [N*P*DATA_WIDTH-1:0] matrix_b;
    output reg done;
    output reg [M*P*DATA_WIDTH-1:0] result_c;

    // Internal registers and wires
    parameter C_DATA_WIDTH = 2 * DATA_WIDTH + 4;
    reg [C_DATA_WIDTH-1:0] sum;

    // State machine definition
    parameter S_IDLE = 2'b00;
    parameter S_CALC = 2'b01;
    parameter S_DONE = 2'b10;

    reg [1:0] state, next_state;

    // Loop counters
    reg [2:0] i;  // For 8x8, need 3 bits
    reg [2:0] j;
    reg [2:0] k;
    
    // Temporary variables for matrix access
    reg signed [DATA_WIDTH-1:0] a_val, b_val;
    reg signed [DATA_WIDTH-1:0] c_array [0:M*P-1];
    
    // Index calculation wires
    wire [5:0] a_index; // 6 bits for up to 64 elements
    wire [5:0] b_index;
    wire [5:0] c_index;
    
    // Declare integer outside always blocks
    integer init_idx;
    integer pack_idx;
    
    assign a_index = i * N + k;
    assign b_index = k * P + j;
    assign c_index = i * P + j;

    // Get matrix
    always @(*) begin
        a_val = matrix_a[(a_index * DATA_WIDTH) +: DATA_WIDTH];
        b_val = matrix_b[(b_index * DATA_WIDTH) +: DATA_WIDTH];
    end

    // Sequential logic for state transitions
    always @(posedge clk or posedge rst) begin
        if (rst) begin
            state <= S_IDLE;
        end else begin
            state <= next_state;
        end
    end

    // Combinational logic for state machine
    always @(*) begin
        next_state = state;
        done = 1'b0;
        
        case (state)
            S_IDLE: begin
                if (start) begin
                    next_state = S_CALC;
                end
            end
            S_CALC: begin
                if (i == M-1 && j == P-1 && k == N-1) begin
                    next_state = S_DONE;
                end
            end
            S_DONE: begin
                done = 1'b1;
                next_state = S_IDLE;
            end
        endcase
    end

    // Main calculation
    always @(posedge clk or posedge rst) begin
        if (rst) begin
            i <= 0;
            j <= 0;
            k <= 0;
            sum <= 0;
            // Initialize c_array to 0
            for (init_idx = 0; init_idx < M*P; init_idx = init_idx + 1) begin
                c_array[init_idx] <= 0;
            end
        end else begin
            if (state == S_CALC) begin
                // Update sum first based on current k value
                if (k == 0) begin
                    sum <= $signed(a_val) * $signed(b_val);
                end else begin
                    sum <= sum + $signed(a_val) * $signed(b_val);
                end

                // Store result when we've completed the dot product
                if (k == N-1) begin
                    c_array[c_index] <= sum + $signed(a_val) * $signed(b_val);
                end

                // Update counters after calculations
                if (k < N - 1) begin
                    k <= k + 1;
                end else begin
                    k <= 0;
                    if (j < P - 1) begin
                        j <= j + 1;
                    end else begin
                        j <= 0;
                        if (i < M - 1) begin
                            i <= i + 1;
                        end else begin
                            i <= 0;
                        end
                    end
                end
            end else if (state == S_IDLE && start) begin
                i <= 0;
                j <= 0;
                k <= 0;
                sum <= 0;
            end
        end
    end
    
    // Put the result array back into result_c
    always @(*) begin
        for (pack_idx = 0; pack_idx < M*P; pack_idx = pack_idx + 1) begin
            result_c[(pack_idx * DATA_WIDTH) +: DATA_WIDTH] = c_array[pack_idx];
        end
    end

endmodule

tb_matrix_multiplier.v
module tb_matrix_multiplier;

    // Parameters for an 8x8 multiplier
    parameter DATA_WIDTH = 8;
    parameter M = 8;
    parameter N = 8;
    parameter P = 8;
    
    // Width for the testbench's internal accumulator
    parameter C_DATA_WIDTH = 2 * DATA_WIDTH + 4;

    // Testbench signals
    reg clk;
    reg rst;
    reg start;

    reg [M*N*DATA_WIDTH-1:0] matrix_a_packed;
    reg [N*P*DATA_WIDTH-1:0] matrix_b_packed;

    wire done;
    wire [M*P*DATA_WIDTH-1:0] result_c_tb;

    reg signed [DATA_WIDTH-1:0] matrix_a_tb [0:M*N-1];
    reg signed [DATA_WIDTH-1:0] matrix_b_tb [0:N*P-1];
    reg signed [DATA_WIDTH-1:0] expected_c [0:M-1][0:P-1];
    
    // Declare integers outside always blocks
    integer pack_i;
    integer i, j, k;
    reg signed [C_DATA_WIDTH-1:0] temp_sum;
    reg signed [DATA_WIDTH-1:0] val_a, val_b;
    integer error_count;
    reg signed [DATA_WIDTH-1:0] dut_val;
    
    // Pack the matrices for the DUT
    always @(*) begin
        for (pack_i = 0; pack_i < M*N; pack_i = pack_i + 1) begin
            matrix_a_packed[pack_i*DATA_WIDTH +: DATA_WIDTH] = matrix_a_tb[pack_i];
        end
        for (pack_i = 0; pack_i < N*P; pack_i = pack_i + 1) begin
            matrix_b_packed[pack_i*DATA_WIDTH +: DATA_WIDTH] = matrix_b_tb[pack_i];
        end
    end
    
    // Instantiate the Unit Under Test (UUT)
    matrix_multiplier #(
        .DATA_WIDTH(DATA_WIDTH),
        .M(M),
        .N(N),
        .P(P)
    ) uut (
        .clk(clk),
        .rst(rst),
        .start(start),
        .matrix_a(matrix_a_packed),
        .matrix_b(matrix_b_packed),
        .done(done),
        .result_c(result_c_tb)
    );

    // Clock generation
    initial begin
        clk = 0;
        forever #5 clk = ~clk;
    end

    
    initial begin
        $display("-------------------------------------------");
        $display("Starting 8x8 Matrix Multiplication Testbench");
        $display("-------------------------------------------");

        // Initialize
        rst = 1;
        start = 0;        
        
        $readmemh("ram_a_init.txt", matrix_a_tb);
        $readmemh("ram_b_init.txt", matrix_b_tb);
        $display("Time: %0t ns | Matrices A and B initialized.", $time);

        // Calculate
        for (i = 0; i < M; i = i + 1) begin
            for (j = 0; j < P; j = j + 1) begin
                temp_sum = 0;
                for (k = 0; k < N; k = k + 1) begin
                    val_a = matrix_a_tb[i*N + k];
                    val_b = matrix_b_tb[k*P + j];
                    temp_sum = temp_sum + (val_a * val_b);
                end
                expected_c[i][j] = temp_sum[DATA_WIDTH-1:0];
            end
        end
        $display("Time: %0t ns | Expected model calculated the expected result.", $time);

        
        #10;
        rst = 0;
        #10;
        start = 1;
        #10;
        start = 0;
        $display("Time: %0t ns | Start pulse sent to DUT. Waiting for completion...", $time);

        
        wait (done);
        #1;
        $display("Time: %0t ns | DUT finished. 'done' signal received.", $time);

        // Compare
        error_count = 0;
        for (i = 0; i < M; i = i + 1) begin
            for (j = 0; j < P; j = j + 1) begin
                dut_val = result_c_tb[((i*P + j) * DATA_WIDTH) +: DATA_WIDTH];
                if (dut_val !== expected_c[i][j]) begin
                    $display("ERROR: Mismatch at C[%0d][%0d]!", i, j);
                    $display("  --> Expected: %h (%d), DUT Result: %h (%d)", 
                             expected_c[i][j], expected_c[i][j], dut_val, dut_val);
                    error_count = error_count + 1;
                end
            end
        end

        if (error_count == 0) begin
            $display("\nSUCCESS: All %0d elements match the expected result!", M*P);
        end else begin
            $display("\nFAILURE: Found %0d mismatches.", error_count);
        end
        
        $display("-------------------------------------------");
        $display("Testbench finished.");
        $display("-------------------------------------------");
        $finish;
    end

    // generate VCD file

    initial begin

        $dumpfile("matrix_multiplier.vcd");   // Name of the VCD file to create
        $dumpvars(0, tb_matrix_multiplier);     // Dump all signals from module "testbench"

    end

endmodule

matrix_multiplier.vcd
$date
	Fri Sep 26 15:21:25 2025
$end
$version
	Icarus Verilog
$end
$timescale
	1s
$end
$scope module tb_matrix_multiplier $end
$var wire 512 ! result_c_tb [511:0] $end
$var wire 1 " done $end
$var parameter 65 # C_DATA_WIDTH $end
$var parameter 32 $ DATA_WIDTH $end
$var parameter 32 % M $end
$var parameter 32 & N $end
$var parameter 32 ' P $end
$var reg 1 ( clk $end
$var reg 8 ) dut_val [7:0] $end
$var reg 512 * matrix_a_packed [511:0] $end
$var reg 512 + matrix_b_packed [511:0] $end
$var reg 1 , rst $end
$var reg 1 - start $end
$var reg 20 . temp_sum [19:0] $end
$var reg 8 / val_a [7:0] $end
$var reg 8 0 val_b [7:0] $end
$var integer 32 1 error_count [31:0] $end
$var integer 32 2 i [31:0] $end
$var integer 32 3 j [31:0] $end
$var integer 32 4 k [31:0] $end
$var integer 32 5 pack_i [31:0] $end
$scope module uut $end
$var wire 1 ( clk $end
$var wire 512 6 matrix_a [511:0] $end
$var wire 512 7 matrix_b [511:0] $end
$var wire 1 , rst $end
$var wire 1 - start $end
$var wire 6 8 c_index [5:0] $end
$var wire 6 9 b_index [5:0] $end
$var wire 6 : a_index [5:0] $end
$var parameter 65 ; C_DATA_WIDTH $end
$var parameter 32 < DATA_WIDTH $end
$var parameter 32 = M $end
$var parameter 32 > N $end
$var parameter 32 ? P $end
$var parameter 2 @ S_CALC $end
$var parameter 2 A S_DONE $end
$var parameter 2 B S_IDLE $end
$var reg 8 C a_val [7:0] $end
$var reg 8 D b_val [7:0] $end
$var reg 1 " done $end
$var reg 3 E i [2:0] $end
$var reg 3 F j [2:0] $end
$var reg 3 G k [2:0] $end
$var reg 2 H next_state [1:0] $end
$var reg 512 I result_c [511:0] $end
$var reg 2 J state [1:0] $end
$var reg 20 K sum [19:0] $end
$var integer 32 L init_idx [31:0] $end
$var integer 32 M pack_idx [31:0] $end
$upscope $end
$upscope $end
$enddefinitions $end
$comment Show the parameter values. $end
$dumpall
b0 B
b10 A
b1 @
b1000 ?
b1000 >
b1000 =
b1000 <
b10100 ;
b1000 '
b1000 &
b1000 %
b1000 $
b10100 #
$end
#0
$dumpvars
b1000000 M
b1000000 L
b0 K
b0 J
b0 I
b0 H
b0 G
b0 F
b0 E
b10000 D
b0 C
b0 :
b0 9
b0 8
b10000000100010000000000000000000100000000000000000001000000010001000100010000000000000000000100000000000100000001000000000000000000010001000000000001000100010000000100010000000100010000000000010001000000010001000100010001000000000000000100010000000000000001000100000001000000000001000100010001000100000000000000000000000000010000000100010000000100010001000000010001000100010001000000010000000000000000000000010001000100000001000100000001000100010001000000010001000000000000000000000001000100000000000000010000 7
b100000001000000010000000000000000000100010001000100000000000000000000000000010000000100010000000100010001000100000000000100010001000000010001000100010001000000010001000100010000000100000001000100010000000100000000000000010000000000000000000100000000000100010001000000000001000000000001000100000001000000010001000100010000000100000001000000000000000100000001000100000000000100010001000100000000000100000001000000000001000100000000000100000001000000010001000100000000000000010001000000000000000100000000 6
b1000000 5
b1000 4
b1000 3
b1000 2
bx 1
b10000 0
b0 /
b10001000001 .
0-
1,
b10000000100010000000000000000000100000000000000000001000000010001000100010000000000000000000100000000000100000001000000000000000000010001000000000001000100010000000100010000000100010000000000010001000000010001000100010001000000000000000100010000000000000001000100000001000000000001000100010001000100000000000000000000000000010000000100010000000100010001000000010001000100010001000000010000000000000000000000010001000100000001000100000001000100010001000000010001000000000000000000000001000100000000000000010000 +
b100000001000000010000000000000000000100010001000100000000000000000000000000010000000100010000000100010001000100000000000100010001000000010001000100010001000000010001000100010000000100000001000100010000000100000000000000010000000000000000000100000000000100010001000000000001000000000001000100000001000000010001000100010000000100000001000000000000000100000001000100000000000100010001000100000000000100000001000000000001000100000000000100000001000000010001000100000000000000010001000000000000000100000000 *
bx )
0(
0"
b0 !
$end
#5
b1000000 L
1(
#10
0(
0,
#15
1(
#20
b1 H
0(
1-
#25
b1 J
1(
#30
0(
0-
#35
b10001 D
b1 C
b1 :
b1000 9
b1 G
1(
#40
0(
#45
b10000 D
b0 C
b10 :
b10000 9
b10 G
b10001 K
1(
#50
0(
#55
b0 D
b10001 C
b11 :
b11000 9
b11 G
1(
#60
0(
#65
b0 C
b100 :
b100000 9
b100 G
1(
#70
0(
#75
b10000 C
b101 :
b101000 9
b101 G
1(
#80
0(
#85
b10001 C
b110 :
b110000 9
b110 G
1(
#90
0(
#95
b1 D
b10000 C
b111 :
b111000 9
b111 G
1(
#100
0(
#105
b0 D
b0 C
b1 8
b0 :
b1 9
b100001 !
b100001 I
b1000000 M
b1 F
b0 G
b100001 K
1(
#110
0(
#115
b1 D
b1 C
b1 :
b1001 9
b1 G
b0 K
1(
#120
0(
#125
b10001 D
b0 C
b10 :
b10001 9
b10 G
b1 K
1(
#130
0(
#135
b0 D
b10001 C
b11 :
b11001 9
b11 G
1(
#140
0(
#145
b10000 D
b0 C
b100 :
b100001 9
b100 G
1(
#150
0(
#155
b10001 D
b10000 C
b101 :
b101001 9
b101 G
1(
#160
0(
#165
b10000 D
b10001 C
b110 :
b110001 9
b110 G
b100010001 K
1(
#170
0(
#175
b1 D
b10000 C
b111 :
b111001 9
b111 G
b1000100001 K
1(
#180
0(
#185
b10000 D
b0 C
b10 8
b0 :
b10 9
b11000100100001 !
b11000100100001 I
b1000000 M
b10 F
b0 G
b1000110001 K
1(
#190
0(
#195
b10001 D
b1 C
b1 :
b1010 9
b1 G
b0 K
1(
#200
0(
#205
b0 C
b10 :
b10010 9
b10 G
b10001 K
1(
#210
0(
#215
b10000 D
b10001 C
b11 :
b11010 9
b11 G
1(
#220
0(
#225
b1 D
b0 C
b100 :
b100010 9
b100 G
b100100001 K
1(
#230
0(
#235
b10000 D
b10000 C
b101 :
b101010 9
b101 G
1(
#240
0(
#245
b10001 C
b110 :
b110010 9
b110 G
b1000100001 K
1(
#250
0(
#255
b0 D
b10000 C
b111 :
b111010 9
b111 G
b1100110001 K
1(
#260
0(
#265
b1 D
b0 C
b11 8
b0 :
b11 9
b1100010011000100100001 !
b1100010011000100100001 I
b1000000 M
b11 F
b0 G
1(
#270
0(
#275
b10000 D
b1 C
b1 :
b1011 9
b1 G
b0 K
1(
#280
0(
#285
b0 C
b10 :
b10011 9
b10 G
b10000 K
1(
#290
0(
#295
b10001 D
b10001 C
b11 :
b11011 9
b11 G
1(
#300
0(
#305
b0 D
b0 C
b100 :
b100011 9
b100 G
b100110001 K
1(
#310
0(
#315
b1 D
b10000 C
b101 :
b101011 9
b101 G
1(
#320
0(
#325
b0 D
b10001 C
b110 :
b110011 9
b110 G
b101000001 K
1(
#330
0(
#335
b10000 D
b10000 C
b111 :
b111011 9
b111 G
1(
#340
0(
#345
b0 D
b0 C
b100 8
b0 :
b100 9
b1000001001100010011000100100001 !
b1000001001100010011000100100001 I
b1000000 M
b100 F
b0 G
b1001000001 K
1(
#350
0(
#355
b10001 D
b1 C
b1 :
b1100 9
b1 G
b0 K
1(
#360
0(
#365
b0 C
b10 :
b10100 9
b10 G
b10001 K
1(
#370
0(
#375
b10001 C
b11 :
b11100 9
b11 G
1(
#380
0(
#385
b0 C
b100 :
b100100 9
b100 G
b100110010 K
1(
#390
0(
#395
b10000 C
b101 :
b101100 9
b101 G
1(
#400
0(
#405
b1 D
b10001 C
b110 :
b110100 9
b110 G
b1001000010 K
1(
#410
0(
#415
b0 D
b10000 C
b111 :
b111100 9
b111 G
b1001010011 K
1(
#420
0(
#425
b0 C
b101 8
b0 :
b101 9
b101001101000001001100010011000100100001 !
b101001101000001001100010011000100100001 I
b1000000 M
b101 F
b0 G
1(
#430
0(
#435
b1 C
b1 :
b1101 9
b1 G
b0 K
1(
#440
0(
#445
b10000 D
b0 C
b10 :
b10101 9
b10 G
1(
#450
0(
#455
b0 D
b10001 C
b11 :
b11101 9
b11 G
1(
#460
0(
#465
b10001 D
b0 C
b100 :
b100101 9
b100 G
1(
#470
0(
#475
b1 D
b10000 C
b101 :
b101101 9
b101 G
1(
#480
0(
#485
b0 D
b10001 C
b110 :
b110101 9
b110 G
b10000 K
1(
#490
0(
#495
b10000 C
b111 :
b111101 9
b111 G
1(
#500
0(
#505
b10001 D
b0 C
b110 8
b0 :
b110 9
b100000101001101000001001100010011000100100001 !
b100000101001101000001001100010011000100100001 I
b1000000 M
b110 F
b0 G
1(
#510
0(
#515
b0 D
b1 C
b1 :
b1110 9
b1 G
b0 K
1(
#520
0(
#525
b1 D
b0 C
b10 :
b10110 9
b10 G
1(
#530
0(
#535
b10001 C
b11 :
b11110 9
b11 G
1(
#540
0(
#545
b0 C
b100 :
b100110 9
b100 G
b10001 K
1(
#550
0(
#555
b10000 D
b10000 C
b101 :
b101110 9
b101 G
1(
#560
0(
#565
b10001 C
b110 :
b110110 9
b110 G
b100010001 K
1(
#570
0(
#575
b10001 D
b10000 C
b111 :
b111110 9
b111 G
b1000100001 K
1(
#580
0(
#585
b10000 D
b0 C
b111 8
b0 :
b111 9
b110001000100000101001101000001001100010011000100100001 !
b110001000100000101001101000001001100010011000100100001 I
b1000000 M
b111 F
b0 G
b1100110001 K
1(
#590
0(
#595
b1 C
b1 :
b1111 9
b1 G
b0 K
1(
#600
0(
#605
b1 D
b0 C
b10 :
b10111 9
b10 G
b10000 K
1(
#610
0(
#615
b10001 D
b10001 C
b11 :
b11111 9
b11 G
1(
#620
0(
#625
b0 C
b100 :
b100111 9
b100 G
b100110001 K
1(
#630
0(
#635
b1 D
b10000 C
b101 :
b101111 9
b101 G
1(
#640
0(
#645
b10001 D
b10001 C
b110 :
b110111 9
b110 G
b101000001 K
1(
#650
0(
#655
b10000 D
b10000 C
b111 :
b111111 9
b111 G
b1001100010 K
1(
#660
0(
#665
b1000 8
b1000 :
b0 9
b110001000110001000100000101001101000001001100010011000100100001 !
b110001000110001000100000101001101000001001100010011000100100001 I
b1000000 M
b1 E
b0 F
b0 G
b1101100010 K
1(
#670
0(
#675
b10001 D
b0 C
b1001 :
b1000 9
b1 G
b100000000 K
1(
#680
0(
#685
b10000 D
b10001 C
b1010 :
b10000 9
b10 G
1(
#690
0(
#695
b0 D
b0 C
b1011 :
b11000 9
b11 G
b1000010000 K
1(
#700
0(
#705
b1 C
b1100 :
b100000 9
b100 G
1(
#710
0(
#715
b1101 :
b101000 9
b101 G
1(
#720
0(
#725
b10000 C
b1110 :
b110000 9
b110 G
1(
#730
0(
#735
b1 D
b10001 C
b1111 :
b111000 9
b111 G
1(
#740
0(
#745
b0 D
b10000 C
b1001 8
b1000 :
b1 9
b1000010110001000110001000100000101001101000001001100010011000100100001 !
b1000010110001000110001000100000101001101000001001100010011000100100001 I
b1000000 M
b1 F
b0 G
b1000100001 K
1(
#750
0(
#755
b1 D
b0 C
b1001 :
b1001 9
b1 G
b0 K
1(
#760
0(
#765
b10001 D
b10001 C
b1010 :
b10001 9
b10 G
1(
#770
0(
#775
b0 D
b0 C
b1011 :
b11001 9
b11 G
b100100001 K
1(
#780
0(
#785
b10000 D
b1 C
b1100 :
b100001 9
b100 G
1(
#790
0(
#795
b10001 D
b1101 :
b101001 9
b101 G
b100110001 K
1(
#800
0(
#805
b10000 D
b10000 C
b1110 :
b110001 9
b110 G
b101000010 K
1(
#810
0(
#815
b1 D
b10001 C
b1111 :
b111001 9
b111 G
b1001000010 K
1(
#820
0(
#825
b10000 D
b10000 C
b1010 8
b1000 :
b10 9
b1010011001000010110001000110001000100000101001101000001001100010011000100100001 !
b1010011001000010110001000110001000100000101001101000001001100010011000100100001 I
b1000000 M
b10 F
b0 G
b1001010011 K
1(
#830
0(
#835
b10001 D
b0 C
b1001 :
b1010 9
b1 G
b100000000 K
1(
#840
0(
#845
b10001 C
b1010 :
b10010 9
b10 G
1(
#850
0(
#855
b10000 D
b0 C
b1011 :
b11010 9
b11 G
b1000100001 K
1(
#860
0(
#865
b1 D
b1 C
b1100 :
b100010 9
b100 G
1(
#870
0(
#875
b10000 D
b1101 :
b101010 9
b101 G
b1000100010 K
1(
#880
0(
#885
b10000 C
b1110 :
b110010 9
b110 G
b1000110010 K
1(
#890
0(
#895
b0 D
b10001 C
b1111 :
b111010 9
b111 G
b1100110010 K
1(
#900
0(
#905
b1 D
b10000 C
b1011 8
b1000 :
b11 9
b11001001010011001000010110001000110001000100000101001101000001001100010011000100100001 !
b11001001010011001000010110001000110001000100000101001101000001001100010011000100100001 I
b1000000 M
b11 F
b0 G
1(
#910
0(
#915
b10000 D
b0 C
b1001 :
b1011 9
b1 G
b10000 K
1(
#920
0(
#925
b10001 C
b1010 :
b10011 9
b10 G
1(
#930
0(
#935
b10001 D
b0 C
b1011 :
b11011 9
b11 G
b100100000 K
1(
#940
0(
#945
b0 D
b1 C
b1100 :
b100011 9
b100 G
1(
#950
0(
#955
b1 D
b1101 :
b101011 9
b101 G
1(
#960
0(
#965
b0 D
b10000 C
b1110 :
b110011 9
b110 G
b100100001 K
1(
#970
0(
#975
b10000 D
b10001 C
b1111 :
b111011 9
b111 G
1(
#980
0(
#985
b0 D
b10000 C
b1100 8
b1000 :
b100 9
b1100010011001001010011001000010110001000110001000100000101001101000001001100010011000100100001 !
b1100010011001001010011001000010110001000110001000100000101001101000001001100010011000100100001 I
b1000000 M
b100 F
b0 G
b1000110001 K
1(
#990
0(
#995
b10001 D
b0 C
b1001 :
b1100 9
b1 G
b0 K
1(
#1000
0(
#1005
b10001 C
b1010 :
b10100 9
b10 G
1(
#1010
0(
#1015
b0 C
b1011 :
b11100 9
b11 G
b100100001 K
1(
#1020
0(
#1025
b1 C
b1100 :
b100100 9
b100 G
1(
#1030
0(
#1035
b1101 :
b101100 9
b101 G
b100110010 K
1(
#1040
0(
#1045
b1 D
b10000 C
b1110 :
b110100 9
b110 G
b101000011 K
1(
#1050
0(
#1055
b0 D
b10001 C
b1111 :
b111100 9
b111 G
b101010011 K
1(
#1060
0(
#1065
b10000 C
b1101 8
b1000 :
b101 9
b1010011001100010011001001010011001000010110001000110001000100000101001101000001001100010011000100100001 !
b1010011001100010011001001010011001000010110001000110001000100000101001101000001001100010011000100100001 I
b1000000 M
b101 F
b0 G
1(
#1070
0(
#1075
b0 C
b1001 :
b1101 9
b1 G
b0 K
1(
#1080
0(
#1085
b10000 D
b10001 C
b1010 :
b10101 9
b10 G
1(
#1090
0(
#1095
b0 D
b0 C
b1011 :
b11101 9
b11 G
b100010000 K
1(
#1100
0(
#1105
b10001 D
b1 C
b1100 :
b100101 9
b100 G
1(
#1110
0(
#1115
b1 D
b1101 :
b101101 9
b101 G
b100100001 K
1(
#1120
0(
#1125
b0 D
b10000 C
b1110 :
b110101 9
b110 G
b100100010 K
1(
#1130
0(
#1135
b10001 C
b1111 :
b111101 9
b111 G
1(
#1140
0(
#1145
b10001 D
b10000 C
b1110 8
b1000 :
b110 9
b10001001010011001100010011001001010011001000010110001000110001000100000101001101000001001100010011000100100001 !
b10001001010011001100010011001001010011001000010110001000110001000100000101001101000001001100010011000100100001 I
b1000000 M
b110 F
b0 G
1(
#1150
0(
#1155
b0 D
b0 C
b1001 :
b1110 9
b1 G
b100010000 K
1(
#1160
0(
#1165
b1 D
b10001 C
b1010 :
b10110 9
b10 G
1(
#1170
0(
#1175
b0 C
b1011 :
b11110 9
b11 G
b100100001 K
1(
#1180
0(
#1185
b1 C
b1100 :
b100110 9
b100 G
1(
#1190
0(
#1195
b10000 D
b1101 :
b101110 9
b101 G
b100100010 K
1(
#1200
0(
#1205
b10000 C
b1110 :
b110110 9
b110 G
b100110010 K
1(
#1210
0(
#1215
b10001 D
b10001 C
b1111 :
b111110 9
b111 G
b1000110010 K
1(
#1220
0(
#1225
b10000 D
b10000 C
b1111 8
b1000 :
b111 9
b10100110010001001010011001100010011001001010011001000010110001000110001000100000101001101000001001100010011000100100001 !
b10100110010001001010011001100010011001001010011001000010110001000110001000100000101001101000001001100010011000100100001 I
b1000000 M
b111 F
b0 G
b1101010011 K
1(
#1230
0(
#1235
b0 C
b1001 :
b1111 9
b1 G
b100000000 K
1(
#1240
0(
#1245
b1 D
b10001 C
b1010 :
b10111 9
b10 G
1(
#1250
0(
#1255
b10001 D
b0 C
b1011 :
b11111 9
b11 G
b100010001 K
1(
#1260
0(
#1265
b1 C
b1100 :
b100111 9
b100 G
1(
#1270
0(
#1275
b1 D
b1101 :
b101111 9
b101 G
b100100010 K
1(
#1280
0(
#1285
b10001 D
b10000 C
b1110 :
b110111 9
b110 G
b100100011 K
1(
#1290
0(
#1295
b10000 D
b10001 C
b1111 :
b111111 9
b111 G
b1000110011 K
1(
#1300
0(
#1305
b1 C
b10000 8
b10000 :
b0 9
b1000011010100110010001001010011001100010011001001010011001000010110001000110001000100000101001101000001001100010011000100100001 !
b1000011010100110010001001010011001100010011001001010011001000010110001000110001000100000101001101000001001100010011000100100001 I
b1000000 M
b10 E
b0 F
b0 G
b1101000011 K
1(
#1310
0(
#1315
b10001 D
b10000 C
b10001 :
b1000 9
b1 G
b10000 K
1(
#1320
0(
#1325
b10000 D
b1 C
b10010 :
b10000 9
b10 G
b100100000 K
1(
#1330
0(
#1335
b0 D
b10011 :
b11000 9
b11 G
b100110000 K
1(
#1340
0(
#1345
b0 C
b10100 :
b100000 9
b100 G
1(
#1350
0(
#1355
b1 C
b10101 :
b101000 9
b101 G
1(
#1360
0(
#1365
b10110 :
b110000 9
b110 G
1(
#1370
0(
#1375
b1 D
b10001 C
b10111 :
b111000 9
b111 G
1(
#1380
0(
#1385
b0 D
b1 C
b10001 8
b10000 :
b1 9
b100000101000011010100110010001001010011001100010011001001010011001000010110001000110001000100000101001101000001001100010011000100100001 !
b100000101000011010100110010001001010011001100010011001001010011001000010110001000110001000100000101001101000001001100010011000100100001 I
b1000000 M
b1 F
b0 G
b101000001 K
1(
#1390
0(
#1395
b1 D
b10000 C
b10001 :
b1001 9
b1 G
b0 K
1(
#1400
0(
#1405
b10001 D
b1 C
b10010 :
b10001 9
b10 G
b10000 K
1(
#1410
0(
#1415
b0 D
b10011 :
b11001 9
b11 G
b100001 K
1(
#1420
0(
#1425
b10000 D
b0 C
b10100 :
b100001 9
b100 G
1(
#1430
0(
#1435
b10001 D
b1 C
b10101 :
b101001 9
b101 G
1(
#1440
0(
#1445
b10000 D
b10110 :
b110001 9
b110 G
b110010 K
1(
#1450
0(
#1455
b1 D
b10001 C
b10111 :
b111001 9
b111 G
b1000010 K
1(
#1460
0(
#1465
b10000 D
b1 C
b10010 8
b10000 :
b10 9
b10100110100000101000011010100110010001001010011001100010011001001010011001000010110001000110001000100000101001101000001001100010011000100100001 !
b10100110100000101000011010100110010001001010011001100010011001001010011001000010110001000110001000100000101001101000001001100010011000100100001 I
b1000000 M
b10 F
b0 G
b1010011 K
1(
#1470
0(
#1475
b10001 D
b10000 C
b10001 :
b1010 9
b1 G
b10000 K
1(
#1480
0(
#1485
b1 C
b10010 :
b10010 9
b10 G
b100100000 K
1(
#1490
0(
#1495
b10000 D
b10011 :
b11010 9
b11 G
b100110001 K
1(
#1500
0(
#1505
b1 D
b0 C
b10100 :
b100010 9
b100 G
b101000001 K
1(
#1510
0(
#1515
b10000 D
b1 C
b10101 :
b101010 9
b101 G
1(
#1520
0(
#1525
b10110 :
b110010 9
b110 G
b101010001 K
1(
#1530
0(
#1535
b0 D
b10001 C
b10111 :
b111010 9
b111 G
b101100001 K
1(
#1540
0(
#1545
b1 D
b1 C
b10011 8
b10000 :
b11 9
b1100001010100110100000101000011010100110010001001010011001100010011001001010011001000010110001000110001000100000101001101000001001100010011000100100001 !
b1100001010100110100000101000011010100110010001001010011001100010011001001010011001000010110001000110001000100000101001101000001001100010011000100100001 I
b1000000 M
b11 F
b0 G
1(
#1550
0(
#1555
b10000 D
b10000 C
b10001 :
b1011 9
b1 G
b1 K
1(
#1560
0(
#1565
b1 C
b10010 :
b10011 9
b10 G
b100000001 K
1(
#1570
0(
#1575
b10001 D
b10011 :
b11011 9
b11 G
b100010001 K
1(
#1580
0(
#1585
b0 D
b0 C
b10100 :
b100011 9
b100 G
b100100010 K
1(
#1590
0(
#1595
b1 D
b1 C
b10101 :
b101011 9
b101 G
1(
#1600
0(
#1605
b0 D
b10110 :
b110011 9
b110 G
b100100011 K
1(
#1610
0(
#1615
b10000 D
b10001 C
b10111 :
b111011 9
b111 G
1(
#1620
0(
#1625
b0 D
b1 C
b10100 8
b10000 :
b100 9
b11001101100001010100110100000101000011010100110010001001010011001100010011001001010011001000010110001000110001000100000101001101000001001100010011000100100001 !
b11001101100001010100110100000101000011010100110010001001010011001100010011001001010011001000010110001000110001000100000101001101000001001100010011000100100001 I
b1000000 M
b100 F
b0 G
b1000110011 K
1(
#1630
0(
#1635
b10001 D
b10000 C
b10001 :
b1100 9
b1 G
b0 K
1(
#1640
0(
#1645
b1 C
b10010 :
b10100 9
b10 G
b100010000 K
1(
#1650
0(
#1655
b10011 :
b11100 9
b11 G
b100100001 K
1(
#1660
0(
#1665
b0 C
b10100 :
b100100 9
b100 G
b100110010 K
1(
#1670
0(
#1675
b1 C
b10101 :
b101100 9
b101 G
1(
#1680
0(
#1685
b1 D
b10110 :
b110100 9
b110 G
b101000011 K
1(
#1690
0(
#1695
b0 D
b10001 C
b10111 :
b111100 9
b111 G
b101000100 K
1(
#1700
0(
#1705
b1 C
b10101 8
b10000 :
b101 9
b10001000011001101100001010100110100000101000011010100110010001001010011001100010011001001010011001000010110001000110001000100000101001101000001001100010011000100100001 !
b10001000011001101100001010100110100000101000011010100110010001001010011001100010011001001010011001000010110001000110001000100000101001101000001001100010011000100100001 I
b1000000 M
b101 F
b0 G
1(
#1710
0(
#1715
b10000 C
b10001 :
b1101 9
b1 G
b0 K
1(
#1720
0(
#1725
b10000 D
b1 C
b10010 :
b10101 9
b10 G
1(
#1730
0(
#1735
b0 D
b10011 :
b11101 9
b11 G
b10000 K
1(
#1740
0(
#1745
b10001 D
b0 C
b10100 :
b100101 9
b100 G
1(
#1750
0(
#1755
b1 D
b1 C
b10101 :
b101101 9
b101 G
1(
#1760
0(
#1765
b0 D
b10110 :
b110101 9
b110 G
b10001 K
1(
#1770
0(
#1775
b10001 C
b10111 :
b111101 9
b111 G
1(
#1780
0(
#1785
b10001 D
b1 C
b10110 8
b10000 :
b110 9
b10001010001000011001101100001010100110100000101000011010100110010001001010011001100010011001001010011001000010110001000110001000100000101001101000001001100010011000100100001 !
b10001010001000011001101100001010100110100000101000011010100110010001001010011001100010011001001010011001000010110001000110001000100000101001101000001001100010011000100100001 I
b1000000 M
b110 F
b0 G
1(
#1790
0(
#1795
b0 D
b10000 C
b10001 :
b1110 9
b1 G
1(
#1800
0(
