matrix_multiplier.v
module matrix_multiplier (
    clk, rst, start, matrix_a, matrix_b, done, result_c
);

    // Parameters
    parameter DATA_WIDTH = 8;
    parameter M = 8; // Rows of matrix A and C
    parameter N = 8; // Cols of matrix A and Rows of matrix B
    parameter P = 8; // Cols of matrix B and C

    input clk;
    input rst;
    input start;
    input [M*N*DATA_WIDTH-1:0] matrix_a;
    input [N*P*DATA_WIDTH-1:0] matrix_b;
    output reg done;
    output reg [M*P*DATA_WIDTH-1:0] result_c;

    // Internal registers and wires
    parameter C_DATA_WIDTH = 2 * DATA_WIDTH + 4;
    reg [C_DATA_WIDTH-1:0] sum;

    // State machine definition
    parameter S_IDLE = 2'b00;
    parameter S_CALC = 2'b01;
    parameter S_DONE = 2'b10;

    reg [1:0] state, next_state;

    // Loop counters
    reg [2:0] i;  // For 8x8, need 3 bits
    reg [2:0] j;
    reg [2:0] k;
    
    // Temporary variables for matrix access
    reg signed [DATA_WIDTH-1:0] a_val, b_val;
    reg signed [DATA_WIDTH-1:0] c_array [0:M*P-1];
    
    // Index calculation wires
    wire [5:0] a_index; // 6 bits for up to 64 elements
    wire [5:0] b_index;
    wire [5:0] c_index;
    
    // Declare integer outside always blocks
    integer init_idx;
    integer pack_idx;
    
    assign a_index = i * N + k;
    assign b_index = k * P + j;
    assign c_index = i * P + j;

    // Get matrix
    always @(*) begin
        a_val = matrix_a[(a_index * DATA_WIDTH) +: DATA_WIDTH];
        b_val = matrix_b[(b_index * DATA_WIDTH) +: DATA_WIDTH];
    end

    // Sequential logic for state transitions
    always @(posedge clk or posedge rst) begin
        if (rst) begin
            state <= S_IDLE;
        end else begin
            state <= next_state;
        end
    end

    // Combinational logic for state machine
    always @(*) begin
        next_state = state;
        done = 1'b0;
        
        case (state)
            S_IDLE: begin
                if (start) begin
                    next_state = S_CALC;
                end
            end
            S_CALC: begin
                if (i == M-1 && j == P-1 && k == N-1) begin
                    next_state = S_DONE;
                end
            end
            S_DONE: begin
                done = 1'b1;
                next_state = S_IDLE;
            end
        endcase
    end

    // Main calculation
    always @(posedge clk or posedge rst) begin
        if (rst) begin
            i <= 0;
            j <= 0;
            k <= 0;
            sum <= 0;
            // Initialize c_array to 0
            for (init_idx = 0; init_idx < M*P; init_idx = init_idx + 1) begin
                c_array[init_idx] <= 0;
            end
        end else begin
            if (state == S_CALC) begin
                // Update sum first based on current k value
                if (k == 0) begin
                    sum <= $signed(a_val) * $signed(b_val);
                end else begin
                    sum <= sum + $signed(a_val) * $signed(b_val);
                end

                // Store result when we've completed the dot product
                if (k == N-1) begin
                    c_array[c_index] <= sum + $signed(a_val) * $signed(b_val);
                end

                // Update counters after calculations
                if (k < N - 1) begin
                    k <= k + 1;
                end else begin
                    k <= 0;
                    if (j < P - 1) begin
                        j <= j + 1;
                    end else begin
                        j <= 0;
                        if (i < M - 1) begin
                            i <= i + 1;
                        end else begin
                            i <= 0;
                        end
                    end
                end
            end else if (state == S_IDLE && start) begin
                i <= 0;
                j <= 0;
                k <= 0;
                sum <= 0;
            end
        end
    end
    
    // Put the result array back into result_c
    always @(*) begin
        for (pack_idx = 0; pack_idx < M*P; pack_idx = pack_idx + 1) begin
            result_c[(pack_idx * DATA_WIDTH) +: DATA_WIDTH] = c_array[pack_idx];
        end
    end

endmodule

tb_matrix_multiplier.v
//==============================================================================
// TESTBENCH
//==============================================================================

`timescale 1ns / 1ps

module tb_matrix_multiplier;

    // Parameters for an 8x8 multiplier
    parameter DATA_WIDTH = 8;
    parameter M = 8;
    parameter N = 8;
    parameter P = 8;
    
    // Width for the testbench's internal accumulator
    parameter C_DATA_WIDTH = 2 * DATA_WIDTH + 4;

    // Testbench signals
    reg clk;
    reg rst;
    reg start;

    reg [M*N*DATA_WIDTH-1:0] matrix_a_packed;
    reg [N*P*DATA_WIDTH-1:0] matrix_b_packed;

    wire done;
    wire [M*P*DATA_WIDTH-1:0] result_c_tb;

    reg signed [DATA_WIDTH-1:0] matrix_a_tb [0:M*N-1];
    reg signed [DATA_WIDTH-1:0] matrix_b_tb [0:N*P-1];
    reg signed [DATA_WIDTH-1:0] expected_c [0:M-1][0:P-1];
    
    // Declare integers outside always blocks
    integer pack_i;
    integer i, j, k;
    reg signed [C_DATA_WIDTH-1:0] temp_sum;
    reg signed [DATA_WIDTH-1:0] val_a, val_b;
    integer error_count;
    reg signed [DATA_WIDTH-1:0] dut_val;
    
    // Pack the matrices for the DUT
    always @(*) begin
        for (pack_i = 0; pack_i < M*N; pack_i = pack_i + 1) begin
            matrix_a_packed[pack_i*DATA_WIDTH +: DATA_WIDTH] = matrix_a_tb[pack_i];
        end
        for (pack_i = 0; pack_i < N*P; pack_i = pack_i + 1) begin
            matrix_b_packed[pack_i*DATA_WIDTH +: DATA_WIDTH] = matrix_b_tb[pack_i];
        end
    end
    
    // Instantiate the Unit Under Test (UUT)
    matrix_multiplier #(
        .DATA_WIDTH(DATA_WIDTH),
        .M(M),
        .N(N),
        .P(P)
    ) uut (
        .clk(clk),
        .rst(rst),
        .start(start),
        .matrix_a(matrix_a_packed),
        .matrix_b(matrix_b_packed),
        .done(done),
        .result_c(result_c_tb)
    );

    // Clock generation (100 MHz)
    initial begin
        clk = 0;
        forever #5 clk = ~clk;
    end

    // Main test sequence
    initial begin
        $display("-------------------------------------------");
        $display("Starting 8x8 Matrix Multiplication Testbench");
        $display("-------------------------------------------");

        // Initialize
        rst = 1;
        start = 0;
        
        // Initialize matrices with simple test pattern if files don't exist
        for (i = 0; i < M*N; i = i + 1) begin
            matrix_a_tb[i] = i % 16; // Simple pattern
        end
        for (i = 0; i < N*P; i = i + 1) begin
            matrix_b_tb[i] = (i + 1) % 16; // Simple pattern
        end
        
        // Try to read input matrices from files (if they exist)
        $readmemh("ram_a_init.txt", matrix_a_tb);
        $readmemh("ram_b_init.txt", matrix_b_tb);
        $display("Time: %0t ns | Matrices A and B initialized.", $time);

        // Calculate the expected result
        for (i = 0; i < M; i = i + 1) begin
            for (j = 0; j < P; j = j + 1) begin
                temp_sum = 0;
                for (k = 0; k < N; k = k + 1) begin
                    val_a = matrix_a_tb[i*N + k];
                    val_b = matrix_b_tb[k*P + j];
                    temp_sum = temp_sum + (val_a * val_b);
                end
                expected_c[i][j] = temp_sum[DATA_WIDTH-1:0];
            end
        end
        $display("Time: %0t ns | Expected model calculated the expected result.", $time);

        // Start the DUT
        #10;
        rst = 0;
        #10;
        start = 1;
        #10;
        start = 0;
        $display("Time: %0t ns | Start pulse sent to DUT. Waiting for completion...", $time);

        // Wait for the DUT to signal it's finished
        wait (done);
        #1;
        $display("Time: %0t ns | DUT finished. 'done' signal received.", $time);

        // Compare the DUT's result with the expected
        error_count = 0;
        for (i = 0; i < M; i = i + 1) begin
            for (j = 0; j < P; j = j + 1) begin
                dut_val = result_c_tb[((i*P + j) * DATA_WIDTH) +: DATA_WIDTH];
                if (dut_val !== expected_c[i][j]) begin
                    $display("ERROR: Mismatch at C[%0d][%0d]!", i, j);
                    $display("  --> Expected: %h (%d), DUT Result: %h (%d)", 
                             expected_c[i][j], expected_c[i][j], dut_val, dut_val);
                    error_count = error_count + 1;
                end
            end
        end

        if (error_count == 0) begin
            $display("\nSUCCESS: All %0d elements match the expected result!", M*P);
        end else begin
            $display("\nFAILURE: Found %0d mismatches.", error_count);
        end
        
        $display("-------------------------------------------");
        $display("Testbench finished.");
        $display("-------------------------------------------");
        $finish;
    end

    // generate VCD file

    initial begin

        $dumpfile("matrix_multiplier.vcd");   // Name of the VCD file to create
        $dumpvars(0, tb_matrix_multiplier);     // Dump all signals from module "testbench"

    end

endmodule

matrix_multiplier.vcd
$date
	Tue Sep 16 10:48:55 2025
$end
$version
	Icarus Verilog
$end
$timescale
	1ps
$end
$scope module tb_matrix_multiplier $end
$var wire 512 ! result_c_tb [511:0] $end
$var wire 1 " done $end
$var parameter 65 # C_DATA_WIDTH $end
$var parameter 32 $ DATA_WIDTH $end
$var parameter 32 % M $end
$var parameter 32 & N $end
$var parameter 32 ' P $end
$var reg 1 ( clk $end
$var reg 8 ) dut_val [7:0] $end
$var reg 512 * matrix_a_packed [511:0] $end
$var reg 512 + matrix_b_packed [511:0] $end
$var reg 1 , rst $end
$var reg 1 - start $end
$var reg 20 . temp_sum [19:0] $end
$var reg 8 / val_a [7:0] $end
$var reg 8 0 val_b [7:0] $end
$var integer 32 1 error_count [31:0] $end
$var integer 32 2 i [31:0] $end
$var integer 32 3 j [31:0] $end
$var integer 32 4 k [31:0] $end
$var integer 32 5 pack_i [31:0] $end
$scope module uut $end
$var wire 1 ( clk $end
$var wire 512 6 matrix_a [511:0] $end
$var wire 512 7 matrix_b [511:0] $end
$var wire 1 , rst $end
$var wire 1 - start $end
$var wire 6 8 c_index [5:0] $end
$var wire 6 9 b_index [5:0] $end
$var wire 6 : a_index [5:0] $end
$var parameter 65 ; C_DATA_WIDTH $end
$var parameter 32 < DATA_WIDTH $end
$var parameter 32 = M $end
$var parameter 32 > N $end
$var parameter 32 ? P $end
$var parameter 2 @ S_CALC $end
$var parameter 2 A S_DONE $end
$var parameter 2 B S_IDLE $end
$var reg 8 C a_val [7:0] $end
$var reg 8 D b_val [7:0] $end
$var reg 1 " done $end
$var reg 3 E i [2:0] $end
$var reg 3 F j [2:0] $end
$var reg 3 G k [2:0] $end
$var reg 2 H next_state [1:0] $end
$var reg 512 I result_c [511:0] $end
$var reg 2 J state [1:0] $end
$var reg 20 K sum [19:0] $end
$var integer 32 L init_idx [31:0] $end
$var integer 32 M pack_idx [31:0] $end
$upscope $end
$upscope $end
$enddefinitions $end
$comment Show the parameter values. $end
$dumpall
b0 B
b10 A
b1 @
b1000 ?
b1000 >
b1000 =
b1000 <
b10100 ;
b1000 '
b1000 &
b1000 %
b1000 $
b10100 #
$end
#0
$dumpvars
b1000000 M
b1000000 L
b0 K
b0 J
b0 I
b0 H
b0 G
b0 F
b0 E
b10000 D
b0 C
b0 :
b0 9
b0 8
b10000000100010000000000000000000100000000000000000001000000010001000100010000000000000000000100000000000100000001000000000000000000010001000000000001000100010000000100010000000100010000000000010001000000010001000100010001000000000000000100010000000000000001000100000001000000000001000100010001000100000000000000000000000000010000000100010000000100010001000000010001000100010001000000010000000000000000000000010001000100000001000100000001000100010001000000010001000000000000000000000001000100000000000000010000 7
b100000001000000010000000000000000000100010001000100000000000000000000000000010000000100010000000100010001000100000000000100010001000000010001000100010001000000010001000100010000000100000001000100010000000100000000000000010000000000000000000100000000000100010001000000000001000000000001000100000001000000010001000100010000000100000001000000000000000100000001000100000000000100010001000100000000000100000001000000000001000100000000000100000001000000010001000100000000000000010001000000000000000100000000 6
b1000000 5
b1000 4
b1000 3
b1000 2
bx 1
b10000 0
b0 /
b10001000001 .
0-
1,
b10000000100010000000000000000000100000000000000000001000000010001000100010000000000000000000100000000000100000001000000000000000000010001000000000001000100010000000100010000000100010000000000010001000000010001000100010001000000000000000100010000000000000001000100000001000000000001000100010001000100000000000000000000000000010000000100010000000100010001000000010001000100010001000000010000000000000000000000010001000100000001000100000001000100010001000000010001000000000000000000000001000100000000000000010000 +
b100000001000000010000000000000000000100010001000100000000000000000000000000010000000100010000000100010001000100000000000100010001000000010001000100010001000000010001000100010000000100000001000100010000000100000000000000010000000000000000000100000000000100010001000000000001000000000001000100000001000000010001000100010000000100000001000000000000000100000001000100000000000100010001000100000000000100000001000000000001000100000000000100000001000000010001000100000000000000010001000000000000000100000000 *
bx )
0(
0"
b0 !
$end
#5000
b1000000 L
1(
#10000
0(
0,
#15000
1(
#20000
b1 H
0(
1-
#25000
b1 J
1(
#30000
0(
0-
#35000
b10001 D
b1 C
b1 :
b1000 9
b1 G
1(
#40000
0(
#45000
b10000 D
b0 C
b10 :
b10000 9
b10 G
b10001 K
1(
#50000
0(
#55000
b0 D
b10001 C
b11 :
b11000 9
b11 G
1(
#60000
0(
#65000
b0 C
b100 :
b100000 9
b100 G
1(
#70000
0(
#75000
b10000 C
b101 :
b101000 9
b101 G
1(
#80000
0(
#85000
b10001 C
b110 :
b110000 9
b110 G
1(
#90000
0(
#95000
b1 D
b10000 C
b111 :
b111000 9
b111 G
1(
#100000
0(
#105000
b0 D
b0 C
b1 8
b0 :
b1 9
b100001 !
b100001 I
b1000000 M
b1 F
b0 G
b100001 K
1(
#110000
0(
#115000
b1 D
b1 C
b1 :
b1001 9
b1 G
b0 K
1(
#120000
0(
#125000
b10001 D
b0 C
b10 :
b10001 9
b10 G
b1 K
1(
#130000
0(
#135000
b0 D
b10001 C
b11 :
b11001 9
b11 G
1(
#140000
0(
#145000
b10000 D
b0 C
b100 :
b100001 9
b100 G
1(
#150000
0(
#155000
b10001 D
b10000 C
b101 :
b101001 9
b101 G
1(
#160000
0(
#165000
b10000 D
b10001 C
b110 :
b110001 9
b110 G
b100010001 K
1(
#170000
0(
#175000
b1 D
b10000 C
b111 :
b111001 9
b111 G
b1000100001 K
1(
#180000
0(
#185000
b10000 D
b0 C
b10 8
b0 :
b10 9
b11000100100001 !
b11000100100001 I
b1000000 M
b10 F
b0 G
b1000110001 K
1(
#190000
0(
#195000
b10001 D
b1 C
b1 :
b1010 9
b1 G
b0 K
1(
#200000
0(
#205000
b0 C
b10 :
b10010 9
b10 G
b10001 K
1(
#210000
0(
#215000
b10000 D
b10001 C
b11 :
b11010 9
b11 G
1(
#220000
0(
#225000
b1 D
b0 C
b100 :
b100010 9
b100 G
b100100001 K
1(
#230000
0(
#235000
b10000 D
b10000 C
b101 :
b101010 9
b101 G
1(
#240000
0(
#245000
b10001 C
b110 :
b110010 9
b110 G
b1000100001 K
1(
#250000
0(
#255000
b0 D
b10000 C
b111 :
b111010 9
b111 G
b1100110001 K
1(
#260000
0(
#265000
b1 D
b0 C
b11 8
b0 :
b11 9
b1100010011000100100001 !
b1100010011000100100001 I
b1000000 M
b11 F
b0 G
1(
#270000
0(
#275000
b10000 D
b1 C
b1 :
b1011 9
b1 G
b0 K
1(
#280000
0(
#285000
b0 C
b10 :
b10011 9
b10 G
b10000 K
1(
#290000
0(
#295000
b10001 D
b10001 C
b11 :
b11011 9
b11 G
1(
#300000
0(
#305000
b0 D
b0 C
b100 :
b100011 9
b100 G
b100110001 K
1(
#310000
0(
#315000
b1 D
b10000 C
b101 :
b101011 9
b101 G
1(
#320000
0(
#325000
b0 D
b10001 C
b110 :
b110011 9
b110 G
b101000001 K
1(
#330000
0(
#335000
b10000 D
b10000 C
b111 :
b111011 9
b111 G
1(
#340000
0(
#345000
b0 D
b0 C
b100 8
b0 :
b100 9
b1000001001100010011000100100001 !
b1000001001100010011000100100001 I
b1000000 M
b100 F
b0 G
b1001000001 K
1(
#350000
0(
#355000
b10001 D
b1 C
b1 :
b1100 9
b1 G
b0 K
1(
#360000
0(
#365000
b0 C
b10 :
b10100 9
b10 G
b10001 K
1(
#370000
0(
#375000
b10001 C
b11 :
b11100 9
b11 G
1(
#380000
0(
#385000
b0 C
b100 :
b100100 9
b100 G
b100110010 K
1(
#390000
0(
#395000
b10000 C
b101 :
b101100 9
b101 G
1(
#400000
0(
#405000
b1 D
b10001 C
b110 :
b110100 9
b110 G
b1001000010 K
1(
#410000
0(
#415000
b0 D
b10000 C
b111 :
b111100 9
b111 G
b1001010011 K
1(
#420000
0(
#425000
b0 C
b101 8
b0 :
b101 9
b101001101000001001100010011000100100001 !
b101001101000001001100010011000100100001 I
b1000000 M
b101 F
b0 G
1(
#430000
0(
#435000
b1 C
b1 :
b1101 9
b1 G
b0 K
1(
#440000
0(
#445000
b10000 D
b0 C
b10 :
b10101 9
b10 G
1(
#450000
0(
#455000
b0 D
b10001 C
b11 :
b11101 9
b11 G
1(
#460000
0(
#465000
b10001 D
b0 C
b100 :
b100101 9
b100 G
1(
#470000
0(
#475000
b1 D
b10000 C
b101 :
b101101 9
b101 G
1(
#480000
0(
#485000
b0 D
b10001 C
b110 :
b110101 9
b110 G
b10000 K
1(
#490000
0(
#495000
b10000 C
b111 :
b111101 9
b111 G
1(
#500000
0(
#505000
b10001 D
b0 C
b110 8
b0 :
b110 9
b100000101001101000001001100010011000100100001 !
b100000101001101000001001100010011000100100001 I
b1000000 M
b110 F
b0 G
1(
#510000
0(
#515000
b0 D
b1 C
b1 :
b1110 9
b1 G
b0 K
1(
#520000
0(
#525000
b1 D
b0 C
b10 :
b10110 9
b10 G
1(
#530000
0(
#535000
b10001 C
b11 :
b11110 9
b11 G
1(
#540000
0(
#545000
b0 C
b100 :
b100110 9
b100 G
b10001 K
1(
#550000
0(
#555000
b10000 D
b10000 C
b101 :
b101110 9
b101 G
1(
#560000
0(
#565000
b10001 C
b110 :
b110110 9
b110 G
b100010001 K
1(
#570000
0(
#575000
b10001 D
b10000 C
b111 :
b111110 9
b111 G
b1000100001 K
1(
#580000
0(
#585000
b10000 D
b0 C
b111 8
b0 :
b111 9
b110001000100000101001101000001001100010011000100100001 !
b110001000100000101001101000001001100010011000100100001 I
b1000000 M
b111 F
b0 G
b1100110001 K
1(
#590000
0(
#595000
b1 C
b1 :
b1111 9
b1 G
b0 K
1(
#600000
0(
#605000
b1 D
b0 C
b10 :
b10111 9
b10 G
b10000 K
1(
#610000
0(
#615000
b10001 D
b10001 C
b11 :
b11111 9
b11 G
1(
#620000
0(
#625000
b0 C
b100 :
b100111 9
b100 G
b100110001 K
1(
#630000
0(
#635000
b1 D
b10000 C
b101 :
b101111 9
b101 G
1(
#640000
0(
#645000
b10001 D
b10001 C
b110 :
b110111 9
b110 G
b101000001 K
1(
#650000
0(
#655000
b10000 D
b10000 C
b111 :
b111111 9
b111 G
b1001100010 K
1(
#660000
0(
#665000
b1000 8
b1000 :
b0 9
b110001000110001000100000101001101000001001100010011000100100001 !
b110001000110001000100000101001101000001001100010011000100100001 I
b1000000 M
b1 E
b0 F
b0 G
b1101100010 K
1(
#670000
0(
#675000
b10001 D
b0 C
b1001 :
b1000 9
b1 G
b100000000 K
1(
#680000
0(
#685000
b10000 D
b10001 C
b1010 :
b10000 9
b10 G
1(
#690000
0(
#695000
b0 D
b0 C
b1011 :
b11000 9
b11 G
b1000010000 K
1(
#700000
0(
#705000
b1 C
b1100 :
b100000 9
b100 G
1(
#710000
0(
#715000
b1101 :
b101000 9
b101 G
1(
#720000
0(
#725000
b10000 C
b1110 :
b110000 9
b110 G
1(
#730000
0(
#735000
b1 D
b10001 C
b1111 :
b111000 9
b111 G
1(
#740000
0(
#745000
b0 D
b10000 C
b1001 8
b1000 :
b1 9
b1000010110001000110001000100000101001101000001001100010011000100100001 !
b1000010110001000110001000100000101001101000001001100010011000100100001 I
b1000000 M
b1 F
b0 G
b1000100001 K
1(
#750000
0(
#755000
b1 D
b0 C
b1001 :
b1001 9
b1 G
b0 K
1(
#760000
0(
#765000
b10001 D
b10001 C
b1010 :
b10001 9
b10 G
1(
#770000
0(
#775000
b0 D
b0 C
b1011 :
b11001 9
b11 G
b100100001 K
1(
#780000
0(
#785000
b10000 D
b1 C
b1100 :
b100001 9
b100 G
1(
#790000
0(
#795000
b10001 D
b1101 :
b101001 9
b101 G
b100110001 K
1(
#800000
0(
#805000
b10000 D
b10000 C
b1110 :
b110001 9
b110 G
b101000010 K
1(
#810000
0(
#815000
b1 D
b10001 C
b1111 :
b111001 9
b111 G
b1001000010 K
1(
#820000
0(
#825000
b10000 D
b10000 C
b1010 8
b1000 :
b10 9
b1010011001000010110001000110001000100000101001101000001001100010011000100100001 !
b1010011001000010110001000110001000100000101001101000001001100010011000100100001 I
b1000000 M
b10 F
b0 G
b1001010011 K
1(
#830000
0(
#835000
b10001 D
b0 C
b1001 :
b1010 9
b1 G
b100000000 K
1(
#840000
0(
#845000
b10001 C
b1010 :
b10010 9
b10 G
1(
#850000
0(
#855000
b10000 D
b0 C
b1011 :
b11010 9
b11 G
b1000100001 K
1(
#860000
0(
#865000
b1 D
b1 C
b1100 :
b100010 9
b100 G
1(
#870000
0(
#875000
b10000 D
b1101 :
b101010 9
b101 G
b1000100010 K
1(
#880000
0(
#885000
b10000 C
b1110 :
b110010 9
b110 G
b1000110010 K
1(
#890000
0(
#895000
b0 D
b10001 C
b1111 :
b111010 9
b111 G
b1100110010 K
1(
#900000
0(
#905000
b1 D
b10000 C
b1011 8
b1000 :
b11 9
b11001001010011001000010110001000110001000100000101001101000001001100010011000100100001 !
b11001001010011001000010110001000110001000100000101001101000001001100010011000100100001 I
b1000000 M
b11 F
b0 G
1(
#910000
0(
#915000
b10000 D
b0 C
b1001 :
b1011 9
b1 G
b10000 K
1(
#920000
0(
#925000
b10001 C
b1010 :
b10011 9
b10 G
1(
#930000
0(
#935000
b10001 D
b0 C
b1011 :
b11011 9
b11 G
b100100000 K
1(
#940000
0(
#945000
b0 D
b1 C
b1100 :
b100011 9
b100 G
1(
#950000
0(
#955000
b1 D
b1101 :
b101011 9
b101 G
1(
#960000
0(
#965000
b0 D
b10000 C
b1110 :
b110011 9
b110 G
b100100001 K
1(
#970000
0(
#975000
b10000 D
b10001 C
b1111 :
b111011 9
b111 G
1(
#980000
0(
#985000
b0 D
b10000 C
b1100 8
b1000 :
b100 9
b1100010011001001010011001000010110001000110001000100000101001101000001001100010011000100100001 !
b1100010011001001010011001000010110001000110001000100000101001101000001001100010011000100100001 I
b1000000 M
b100 F
b0 G
b1000110001 K
1(
#990000
0(
#995000
b10001 D
b0 C
b1001 :
b1100 9
b1 G
b0 K
1(
#1000000
0(
#1005000
b10001 C
b1010 :
b10100 9
b10 G
1(
#1010000
0(
#1015000
b0 C
b1011 :
b11100 9
b11 G
b100100001 K
1(
#1020000
0(
#1025000
b1 C
b1100 :
b100100 9
b100 G
1(
#1030000
0(
#1035000
b1101 :
b101100 9
b101 G
b100110010 K
1(
#1040000
0(
#1045000
b1 D
b10000 C
b1110 :
b110100 9
b110 G
b101000011 K
1(
#1050000
0(
#1055000
b0 D
b10001 C
b1111 :
b111100 9
b111 G
b101010011 K
1(
#1060000
0(
#1065000
b10000 C
b1101 8
b1000 :
b101 9
b1010011001100010011001001010011001000010110001000110001000100000101001101000001001100010011000100100001 !
b1010011001100010011001001010011001000010110001000110001000100000101001101000001001100010011000100100001 I
b1000000 M
b101 F
b0 G
1(
#1070000
0(
#1075000
b0 C
b1001 :
b1101 9
b1 G
b0 K
1(
#1080000
0(
#1085000
b10000 D
b10001 C
b1010 :
b10101 9
b10 G
1(
#1090000
0(
#1095000
b0 D
b0 C
b1011 :
b11101 9
b11 G
b100010000 K
1(
#1100000
0(
#1105000
b10001 D
b1 C
b1100 :
b100101 9
b100 G
1(
#1110000
0(
#1115000
b1 D
b1101 :
b101101 9
b101 G
b100100001 K
1(
#1120000
0(
#1125000
b0 D
b10000 C
b1110 :
b110101 9
b110 G
b100100010 K
1(
#1130000
0(
#1135000
b10001 C
b1111 :
b111101 9
b111 G
1(
#1140000
0(
#1145000
b10001 D
b10000 C
b1110 8
b1000 :
b110 9
b10001001010011001100010011001001010011001000010110001000110001000100000101001101000001001100010011000100100001 !
b10001001010011001100010011001001010011001000010110001000110001000100000101001101000001001100010011000100100001 I
b1000000 M
b110 F
b0 G
1(
#1150000
0(
#1155000
b0 D
b0 C
b1001 :
b1110 9
b1 G
b100010000 K
1(
#1160000
0(
#1165000
b1 D
b10001 C
b1010 :
b10110 9
b10 G
1(
#1170000
0(
#1175000
b0 C
b1011 :
b11110 9
b11 G
b100100001 K
1(
#1180000
0(
#1185000
b1 C
b1100 :
b100110 9
b100 G
1(
#1190000
0(
#1195000
b10000 D
b1101 :
b101110 9
b101 G
b100100010 K
1(
#1200000
0(
#1205000
b10000 C
b1110 :
b110110 9
b110 G
b100110010 K
1(
#1210000
0(
#1215000
b10001 D
b10001 C
b1111 :
b111110 9
b111 G
b1000110010 K
1(
#1220000
0(
#1225000
b10000 D
b10000 C
b1111 8
b1000 :
b111 9
b10100110010001001010011001100010011001001010011001000010110001000110001000100000101001101000001001100010011000100100001 !
b10100110010001001010011001100010011001001010011001000010110001000110001000100000101001101000001001100010011000100100001 I
b1000000 M
b111 F
b0 G
b1101010011 K
1(
#1230000
0(
#1235000
b0 C
b1001 :
b1111 9
b1 G
b100000000 K
1(
#1240000
0(
#1245000
b1 D
b10001 C
b1010 :
b10111 9
b10 G
1(
#1250000
0(
#1255000
b10001 D
b0 C
b1011 :
b11111 9
b11 G
b100010001 K
1(
#1260000
0(
#1265000
b1 C
b1100 :
b100111 9
b100 G
1(
#1270000
0(
#1275000
b1 D
b1101 :
b101111 9
b101 G
b100100010 K
1(
#1280000
0(
#1285000
b10001 D
b10000 C
b1110 :
b110111 9
b110 G
b100100011 K
1(
#1290000
0(
#1295000
b10000 D
b10001 C
b1111 :
b111111 9
b111 G
b1000110011 K
1(
#1300000
0(
#1305000
b1 C
b10000 8
b10000 :
b0 9
b1000011010100110010001001010011001100010011001001010011001000010110001000110001000100000101001101000001001100010011000100100001 !
b1000011010100110010001001010011001100010011001001010011001000010110001000110001000100000101001101000001001100010011000100100001 I
b1000000 M
b10 E
b0 F
b0 G
b1101000011 K
1(
#1310000
0(
#1315000
b10001 D
b10000 C
b10001 :
b1000 9
b1 G
b10000 K
1(
#1320000
0(
#1325000
b10000 D
b1 C
b10010 :
b10000 9
b10 G
b100100000 K
1(
#1330000
0(
#1335000
b0 D
b10011 :
b11000 9
b11 G
b100110000 K
1(
#1340000
0(
#1345000
b0 C
b10100 :
b100000 9
b100 G
1(
#1350000
0(
#1355000
b1 C
b10101 :
b101000 9
b101 G
1(
#1360000
0(
#1365000
b10110 :
b110000 9
b110 G
1(
#1370000
0(
#1375000
b1 D
b10001 C
b10111 :
b111000 9
b111 G
1(
#1380000
0(
#1385000
b0 D
b1 C
b10001 8
b10000 :
b1 9
b100000101000011010100110010001001010011001100010011001001010011001000010110001000110001000100000101001101000001001100010011000100100001 !
b100000101000011010100110010001001010011001100010011001001010011001000010110001000110001000100000101001101000001001100010011000100100001 I
b1000000 M
b1 F
b0 G
b101000001 K
1(
#1390000
0(
#1395000
b1 D
b10000 C
b10001 :
b1001 9
b1 G
b0 K
1(
#1400000
0(
#1405000
b10001 D
b1 C
b10010 :
b10001 9
b10 G
b10000 K
1(
#1410000
0(
#1415000
b0 D
b10011 :
b11001 9
b11 G
b100001 K
1(
#1420000
0(
#1425000
b10000 D
b0 C
b10100 :
b100001 9
b100 G
1(
#1430000
0(
#1435000
b10001 D
b1 C
b10101 :
b101001 9
b101 G
1(
#1440000
0(
#1445000
b10000 D
b10110 :
b110001 9
b110 G
b110010 K
1(
#1450000
0(
#1455000
b1 D
b10001 C
b10111 :
b111001 9
b111 G
b1000010 K
1(
#1460000
0(
#1465000
b10000 D
b1 C
b10010 8
b10000 :
b10 9
b10100110100000101000011010100110010001001010011001100010011001001010011001000010110001000110001000100000101001101000001001100010011000100100001 !
b10100110100000101000011010100110010001001010011001100010011001001010011001000010110001000110001000100000101001101000001001100010011000100100001 I
b1000000 M
b10 F
b0 G
b1010011 K
1(
#1470000
0(
#1475000
b10001 D
b10000 C
b10001 :
b1010 9
b1 G
b10000 K
1(
#1480000
0(
#1485000
b1 C
b10010 :
b10010 9
b10 G
b100100000 K
1(
#1490000
0(
#1495000
b10000 D
b10011 :
b11010 9
b11 G
b100110001 K
1(
#1500000
0(
#1505000
b1 D
b0 C
b10100 :
b100010 9
b100 G
b101000001 K
1(
#1510000
0(
#1515000
b10000 D
b1 C
b10101 :
b101010 9
b101 G
1(
#1520000
0(
#1525000
b10110 :
b110010 9
b110 G
b101010001 K
1(
#1530000
0(
#1535000
b0 D
b10001 C
b10111 :
b111010 9
b111 G
b101100001 K
1(
#1540000
0(
#1545000
b1 D
b1 C
b10011 8
b10000 :
b11 9
b1100001010100110100000101000011010100110010001001010011001100010011001001010011001000010110001000110001000100000101001101000001001100010011000100100001 !
b1100001010100110100000101000011010100110010001001010011001100010011001001010011001000010110001000110001000100000101001101000001001100010011000100100001 I
b1000000 M
b11 F
b0 G
1(
#1550000
0(
#1555000
b10000 D
b10000 C
b10001 :
b1011 9
b1 G
b1 K
1(
#1560000
0(
#1565000
b1 C
b10010 :
b10011 9
b10 G
b100000001 K
1(
#1570000
0(
#1575000
b10001 D
b10011 :
b11011 9
b11 G
b100010001 K
1(
#1580000
0(
#1585000
b0 D
b0 C
b10100 :
b100011 9
b100 G
b100100010 K
1(
#1590000
0(
#1595000
b1 D
b1 C
b10101 :
b101011 9
b101 G
1(
#1600000
0(
#1605000
b0 D
b10110 :
b110011 9
b110 G
b100100011 K
1(
#1610000
0(
#1615000
b10000 D
b10001 C
b10111 :
b111011 9
b111 G
1(
#1620000
0(
#1625000
b0 D
b1 C
b10100 8
b10000 :
b100 9
b11001101100001010100110100000101000011010100110010001001010011001100010011001001010011001000010110001000110001000100000101001101000001001100010011000100100001 !
b11001101100001010100110100000101000011010100110010001001010011001100010011001001010011001000010110001000110001000100000101001101000001001100010011000100100001 I
b1000000 M
b100 F
b0 G
b1000110011 K
1(
#1630000
0(
#1635000
b10001 D
b10000 C
b10001 :
b1100 9
b1 G
b0 K
1(
#1640000
0(
#1645000
b1 C
b10010 :
b10100 9
b10 G
b100010000 K
1(
#1650000
0(
#1655000
b10011 :
b11100 9
b11 G
b100100001 K
1(
#1660000
0(
#1665000
b0 C
b10100 :
b100100 9
b100 G
b100110010 K
1(
#1670000
0(
#1675000
b1 C
b10101 :
b101100 9
b101 G
1(
#1680000
0(
#1685000
b1 D
b10110 :
b110100 9
b110 G
b101000011 K
1(
#1690000
0(
#1695000
b0 D
b10001 C
b10111 :
b111100 9
b111 G
b101000100 K
1(
#1700000
0(
